sigma_backend_duckdb/__init__.py
sigma_backend_duckdb/backend.py
sigma_backend_duckdb/pipelines.py
pysigma_backend_duckdb-0.1.4.dist-info/METADATA
pysigma_backend_duckdb-0.1.4.dist-info/WHEEL
pysigma_backend_duckdb-0.1.4.dist-info/RECORD
