Metadata-Version: 2.4
Name: pySigma-backend-duckdb
Version: 0.1.4
Summary: pySigma DuckDB backend for local Sigma rule validation against JSON logs
Project-URL: Homepage, https://github.com/northsh/pySigma-backend-duckdb
Project-URL: Repository, https://github.com/northsh/pySigma-backend-duckdb
Project-URL: Issues, https://github.com/northsh/pySigma-backend-duckdb/issues
Author-email: "north.sh Labs" <alex@north.sh>
License-Expression: MIT
Keywords: detection,duckdb,pysigma,security,sigma
Classifier: Development Status :: 4 - Beta
Classifier: Intended Audience :: Developers
Classifier: Intended Audience :: Information Technology
Classifier: License :: OSI Approved :: MIT License
Classifier: Operating System :: OS Independent
Classifier: Programming Language :: Python :: 3
Classifier: Programming Language :: Python :: 3.10
Classifier: Programming Language :: Python :: 3.11
Classifier: Programming Language :: Python :: 3.12
Classifier: Topic :: Security
Requires-Python: >=3.10
Requires-Dist: pysigma<2.0.0,>=1.0.0
Provides-Extra: dev
Requires-Dist: pytest-cov>=4.0.0; extra == 'dev'
Requires-Dist: pytest>=8.0.0; extra == 'dev'
Requires-Dist: ruff>=0.4.0; extra == 'dev'
